Metadata-Version: 1.1
Name: hispadocs
Version: 0.1.1
Summary: Package description
